unicodedata2.cpython-38-aarch64-linux-gnu.so
unicodedata2-17.0.0.dist-info/LICENSE
unicodedata2-17.0.0.dist-info/METADATA
unicodedata2-17.0.0.dist-info/WHEEL
unicodedata2-17.0.0.dist-info/top_level.txt
unicodedata2-17.0.0.dist-info/RECORD
