Metadata-Version: 2.1
Name: unicodedata2
Version: 17.0.0
Summary: Unicodedata backport updated to the latest Unicode version.
Home-page: http://github.com/fonttools/unicodedata2
Download-URL: http://github.com/fonttools/unicodedata2
Author: Mike Kaplinskiy
Author-email: mike.kaplinskiy@gmail.com
License: Apache License 2.0
Platform: any
License-File: LICENSE
Provides-Extra: testing
Requires-Dist: pytest ; extra == 'testing'
Requires-Dist: coverage ; extra == 'testing'
Requires-Dist: pytest-xdist ; extra == 'testing'
Requires-Dist: pytest-randomly ; extra == 'testing'
